[{"Name":"Modérateur","Email":"admin@app.net","Password":"S4VzJg+yuLVrtp6gTvyn4ZT5Z3BDVEiqJYgxJWe8Y/I=BkJ2SdJ4hagqUSGplfcYAiynSno=","Access":3,"Blocked":false,"Verified":true,"Notify":true,"Avatar":"/App_Assets/Users/5aa8957d-e980-4cac-b915-aaa63d0909f1.jpeg","Id":1},{"Name":"Charlot","Email":"charlot@yopmail.com","Password":"WrlJ2Wm2NgzA2bjAfyXIheughlqhxwl1Niuv60gVij8=M54D55bnJyGmTUGOmB1gdr1cjxU=","Access":1,"Blocked":false,"Verified":true,"Notify":true,"Avatar":"/App_Assets/Users/no_avatar.png","Id":2},{"Name":"Ariane","Email":"ari76@gmail.com","Password":"fDGzHKrjmKpfFaJSmsmdQGrxwP44zBmH/2av+/CNGUI=IwgZkvXtJ2Dz96Yvf1FhmisBa6Q=","Access":1,"Blocked":false,"Verified":false,"Notify":true,"Avatar":"/App_Assets/Users/no_avatar.png","Id":3},{"Name":"Ariane","Email":"ari77@gmail.com","Password":"ydkX84duZUegC51ucXiRRtUIQljj7aKu0RIWGKhWlhs=V4d8+fQgCYf5RfV+oeP7DFoh8rI=","Access":1,"Blocked":false,"Verified":false,"Notify":true,"Avatar":"/App_Assets/Users/no_avatar.png","Id":4},{"Name":"Thomas","Email":"tomi7676@gmail.com","Password":"wsrkWp+v0AHo4HvB2jxG5HRUad9at4OONsuBOn3mZ0E=Q0/sCsxk0VcjD0sPnX3PA1+tQ7A=","Access":1,"Blocked":false,"Verified":false,"Notify":true,"Avatar":"/App_Assets/Users/a9942fc7-ea7b-4eda-85f8-098c00414b6e.png","Id":5},{"Name":"Edouard","Email":"edstm88@gmail.com","Password":"ZBTz0UP7iiV6Tc3dT5LP6bipD0OadcqKv7/PmY4epWM=NENpVqPIeMxzFbus/9/n4PqBiFI=","Access":1,"Blocked":false,"Verified":true,"Notify":true,"Avatar":"/App_Assets/Users/170d9383-7bb7-4dc5-b081-55a480fa8a9c.jpeg","Id":6}]
